tagscraper/__init__.py
tagscraper/bin.py
tagscraper/scrape.py
tagscraper-1.0.dist-info/METADATA
tagscraper-1.0.dist-info/WHEEL
tagscraper-1.0.dist-info/entry_points.txt
tagscraper-1.0.dist-info/top_level.txt
tagscraper-1.0.dist-info/RECORD
